tespy/__init__.py
tespy/components/__init__.py
tespy/components/component.py
tespy/components/subsystem.py
tespy/components/basics/__init__.py
tespy/components/basics/cycle_closer.py
tespy/components/basics/sink.py
tespy/components/basics/source.py
tespy/components/basics/subsystem_interface.py
tespy/components/combustion/__init__.py
tespy/components/combustion/base.py
tespy/components/combustion/diabatic.py
tespy/components/combustion/engine.py
tespy/components/customs/__init__.py
tespy/components/displacementmachinery/__init__.py
tespy/components/displacementmachinery/base.py
tespy/components/displacementmachinery/polynomial_compressor.py
tespy/components/displacementmachinery/polynomial_compressor_with_cooling.py
tespy/components/heat_exchangers/__init__.py
tespy/components/heat_exchangers/base.py
tespy/components/heat_exchangers/condenser.py
tespy/components/heat_exchangers/desuperheater.py
tespy/components/heat_exchangers/movingboundary.py
tespy/components/heat_exchangers/parabolic_trough.py
tespy/components/heat_exchangers/parallel.py
tespy/components/heat_exchangers/sectioned.py
tespy/components/heat_exchangers/simple.py
tespy/components/heat_exchangers/solar_collector.py
tespy/components/nodes/__init__.py
tespy/components/nodes/base.py
tespy/components/nodes/droplet_separator.py
tespy/components/nodes/drum.py
tespy/components/nodes/merge.py
tespy/components/nodes/node.py
tespy/components/nodes/separator.py
tespy/components/nodes/splitter.py
tespy/components/piping/__init__.py
tespy/components/piping/pipe.py
tespy/components/piping/valve.py
tespy/components/power/__init__.py
tespy/components/power/bus.py
tespy/components/power/generator.py
tespy/components/power/motor.py
tespy/components/power/sink.py
tespy/components/power/source.py
tespy/components/reactors/__init__.py
tespy/components/reactors/fuel_cell.py
tespy/components/reactors/water_electrolyzer.py
tespy/components/turbomachinery/__init__.py
tespy/components/turbomachinery/base.py
tespy-0.9.12.dist-info/licenses/LICENSE
tespy-0.9.12.dist-info/WHEEL
tespy-0.9.12.dist-info/METADATA
tespy-0.9.12.dist-info/RECORD
