Metadata-Version: 2.4
Name: tespy
Version: 0.9.12
Summary: Thermal Engineering Systems in Python (TESPy)
Author-email: Francesco Witte <tespy@witte.sh>
Requires-Python: >=3.10
Classifier: Development Status :: 4 - Beta
Classifier: Intended Audience :: Education
Classifier: Intended Audience :: Science/Research
Classifier: License :: OSI Approved :: MIT License
Classifier: Operating System :: Microsoft :: Windows
Classifier: Operating System :: POSIX
Classifier: Operating System :: Unix
Classifier: Programming Language :: Python
Classifier: Programming Language :: Python :: 3.10
Classifier: Programming Language :: Python :: 3.11
Classifier: Programming Language :: Python :: 3.12
Classifier: Topic :: Scientific/Engineering
License-File: LICENSE
Requires-Dist: CoolProp>=6.8
Requires-Dist: jinja2
Requires-Dist: matplotlib>=3.2.1
Requires-Dist: numpy>=1.13.3
Requires-Dist: pandas>=1.3.0
Requires-Dist: pint
Requires-Dist: scipy
Requires-Dist: tabulate>=0.8.2
Requires-Dist: build ; extra == "dev"
Requires-Dist: flit ; extra == "dev"
Requires-Dist: fluprodia ; extra == "dev"
Requires-Dist: furo ; extra == "dev"
Requires-Dist: iapws ; extra == "dev"
Requires-Dist: isort ; extra == "dev"
Requires-Dist: myst-nb ; extra == "dev"
Requires-Dist: pymoo ; extra == "dev"
Requires-Dist: pyromat ; extra == "dev"
Requires-Dist: pytest ; extra == "dev"
Requires-Dist: sphinx>=7.2.2 ; extra == "dev"
Requires-Dist: sphinx-copybutton ; extra == "dev"
Requires-Dist: sphinx-design ; extra == "dev"
Requires-Dist: sphinx-notfound-page>=1.1.0 ; extra == "dev"
Requires-Dist: sphinxcontrib.bibtex ; extra == "dev"
Requires-Dist: tox ; extra == "dev"
Requires-Dist: twine ; extra == "dev"
Requires-Dist: pymoo ; extra == "opt"
Project-URL: Changelog, https://tespy.readthedocs.io/en/main/whats_new.html
Project-URL: Documentation, https://tespy.readthedocs.io/
Project-URL: Homepage, https://github.com/oemof/tespy
Project-URL: Issue Tracker, https://github.com/oemof/tespy/issues
Provides-Extra: dev
Provides-Extra: opt
